CHANGELOG.rst
MANIFEST.in
README.rst
setup.py
sitesecret.py
sitesecret.egg-info/PKG-INFO
sitesecret.egg-info/SOURCES.txt
sitesecret.egg-info/dependency_links.txt
sitesecret.egg-info/top_level.txt