Metadata-Version: 1.0
Name: sitesecret
Version: 0.1.1
Summary: Generate a per-site random secret
Home-page: UNKNOWN
Author: UNKNOWN
Author-email: UNKNOWN
License: UNKNOWN
Platform: UNKNOWN
